{"last_updated": "2021-02-21 05:00:34 GMT", "keyboards": {"massdrop/ctrl": {"keyboard_name": "CTRL", "keyboard_folder": "massdrop/ctrl", "keymaps": {}, "layouts": {"LAYOUT": {"key_count": 87, "layout": [{"x": 0, "y": 0, "w": 1, "label": "ESCAPE", "matrix": [0, 0]}, {"x": 2, "y": 0, "w": 1, "label": "F1", "matrix": [0, 1]}, {"x": 3, "y": 0, "w": 1, "label": "F2", "matrix": [0, 2]}, {"x": 4, "y": 0, "w": 1, "label": "F3", "matrix": [0, 3]}, {"x": 5, "y": 0, "w": 1, "label": "F4", "matrix": [0, 4]}, {"x": 6.5, "y": 0, "w": 1, "label": "F5", "matrix": [0, 5]}, {"x": 7.5, "y": 0, "w": 1, "label": "F6", "matrix": [0, 6]}, {"x": 8.5, "y": 0, "w": 1, "label": "F7", "matrix": [0, 7]}, {"x": 9.5, "y": 0, "w": 1, "label": "F8", "matrix": [6, 0]}, {"x": 11, "y": 0, "w": 1, "label": "F9", "matrix": [6, 1]}, {"x": 12, "y": 0, "w": 1, "label": "F10", "matrix": [6, 2]}, {"x": 13, "y": 0, "w": 1, "label": "F11", "matrix": [6, 3]}, {"x": 14, "y": 0, "w": 1, "label": "F12", "matrix": [6, 4]}, {"x": 15.5, "y": 0, "w": 1, "label": "PRINT SCREEN", "matrix": [6, 5]}, {"x": 16.5, "y": 0, "w": 1, "label": "SCROLL LOCK", "matrix": [6, 6]}, {"x": 17.5, "y": 0, "w": 1, "label": "PAUSE BREAK", "matrix": [6, 7]}, {"x": 0, "y": 1.5, "w": 1, "label": "BACKTICK", "matrix": [1, 0]}, {"x": 1, "y": 1.5, "w": 1, "label": "1", "matrix": [1, 1]}, {"x": 2, "y": 1.5, "w": 1, "label": "2", "matrix": [1, 2]}, {"x": 3, "y": 1.5, "w": 1, "label": "3", "matrix": [1, 3]}, {"x": 4, "y": 1.5, "w": 1, "label": "4", "matrix": [1, 4]}, {"x": 5, "y": 1.5, "w": 1, "label": "5", "matrix": [1, 5]}, {"x": 6, "y": 1.5, "w": 1, "label": "6", "matrix": [1, 6]}, {"x": 7, "y": 1.5, "w": 1, "label": "7", "matrix": [1, 7]}, {"x": 8, "y": 1.5, "w": 1, "label": "8", "matrix": [7, 0]}, {"x": 9, "y": 1.5, "w": 1, "label": "9", "matrix": [7, 1]}, {"x": 10, "y": 1.5, "w": 1, "label": "0", "matrix": [7, 2]}, {"x": 11, "y": 1.5, "w": 1, "label": "MINUS", "matrix": [7, 3]}, {"x": 12, "y": 1.5, "w": 1, "label": "EQUALS", "matrix": [7, 4]}, {"x": 13, "y": 1.5, "w": 2, "label": "BACKSPACE", "matrix": [7, 5]}, {"x": 15.5, "y": 1.5, "w": 1, "label": "INSERT", "matrix": [7, 6]}, {"x": 16.5, "y": 1.5, "w": 1, "label": "HOME", "matrix": [7, 7]}, {"x": 17.5, "y": 1.5, "w": 1, "label": "PAGE UP", "matrix": [9, 7]}, {"x": 0, "y": 2.5, "w": 1.5, "label": "TAB", "matrix": [2, 0]}, {"x": 1.5, "y": 2.5, "w": 1, "label": "Q", "matrix": [2, 1]}, {"x": 2.5, "y": 2.5, "w": 1, "label": "W", "matrix": [2, 2]}, {"x": 3.5, "y": 2.5, "w": 1, "label": "E", "matrix": [2, 3]}, {"x": 4.5, "y": 2.5, "w": 1, "label": "R", "matrix": [2, 4]}, {"x": 5.5, "y": 2.5, "w": 1, "label": "T", "matrix": [2, 5]}, {"x": 6.5, "y": 2.5, "w": 1, "label": "Y", "matrix": [2, 6]}, {"x": 7.5, "y": 2.5, "w": 1, "label": "U", "matrix": [2, 7]}, {"x": 8.5, "y": 2.5, "w": 1, "label": "I", "matrix": [8, 0]}, {"x": 9.5, "y": 2.5, "w": 1, "label": "O", "matrix": [8, 1]}, {"x": 10.5, "y": 2.5, "w": 1, "label": "P", "matrix": [8, 2]}, {"x": 11.5, "y": 2.5, "w": 1, "label": "LEFT BRACKET", "matrix": [8, 3]}, {"x": 12.5, "y": 2.5, "w": 1, "label": "RIGHT BRACKET", "matrix": [8, 4]}, {"x": 13.5, "y": 2.5, "w": 1.5, "label": "BACK SLASH", "matrix": [8, 5]}, {"x": 15.5, "y": 2.5, "w": 1, "label": "DELETE", "matrix": [8, 6]}, {"x": 16.5, "y": 2.5, "w": 1, "label": "END", "matrix": [8, 7]}, {"x": 17.5, "y": 2.5, "w": 1, "label": "PAGE DOWN", "matrix": [9, 6]}, {"x": 0, "y": 3.5, "w": 1.75, "label": "CAPS LOCK", "matrix": [3, 0]}, {"x": 1.75, "y": 3.5, "w": 1, "label": "A", "matrix": [3, 1]}, {"x": 2.75, "y": 3.5, "w": 1, "label": "S", "matrix": [3, 2]}, {"x": 3.75, "y": 3.5, "w": 1, "label": "D", "matrix": [3, 3]}, {"x": 4.75, "y": 3.5, "w": 1, "label": "F", "matrix": [3, 4]}, {"x": 5.75, "y": 3.5, "w": 1, "label": "G", "matrix": [3, 5]}, {"x": 6.75, "y": 3.5, "w": 1, "label": "H", "matrix": [3, 6]}, {"x": 7.75, "y": 3.5, "w": 1, "label": "J", "matrix": [3, 7]}, {"x": 8.75, "y": 3.5, "w": 1, "label": "K", "matrix": [9, 0]}, {"x": 9.75, "y": 3.5, "w": 1, "label": "L", "matrix": [9, 1]}, {"x": 10.75, "y": 3.5, "w": 1, "label": "SEMICOLON", "matrix": [9, 2]}, {"x": 11.75, "y": 3.5, "w": 1, "label": "SINGLE TICK", "matrix": [9, 3]}, {"x": 12.75, "y": 3.5, "w": 2.25, "label": "ENTER", "matrix": [9, 4]}, {"x": 0, "y": 4.5, "w": 2.25, "label": "LEFT SHIFT", "matrix": [4, 0]}, {"x": 2.25, "y": 4.5, "w": 1, "label": "Z", "matrix": [4, 1]}, {"x": 3.25, "y": 4.5, "w": 1, "label": "X", "matrix": [4, 2]}, {"x": 4.25, "y": 4.5, "w": 1, "label": "C", "matrix": [4, 3]}, {"x": 5.25, "y": 4.5, "w": 1, "label": "V", "matrix": [4, 4]}, {"x": 6.25, "y": 4.5, "w": 1, "label": "B", "matrix": [4, 5]}, {"x": 7.25, "y": 4.5, "w": 1, "label": "N", "matrix": [4, 6]}, {"x": 8.25, "y": 4.5, "w": 1, "label": "M", "matrix": [4, 7]}, {"x": 9.25, "y": 4.5, "w": 1, "label": "COMMA", "matrix": [10, 0]}, {"x": 10.25, "y": 4.5, "w": 1, "label": "PERIOD", "matrix": [10, 1]}, {"x": 11.25, "y": 4.5, "w": 1, "label": "FORWARD SLASH", "matrix": [10, 2]}, {"x": 12.25, "y": 4.5, "w": 2.75, "label": "RIGHT SHIFT", "matrix": [10, 3]}, {"x": 16.5, "y": 4.5, "w": 1, "label": "UP ARROW", "matrix": [9, 5]}, {"x": 0.005, "y": 5.5, "w": 1.25, "label": "LEFT CTRL", "matrix": [5, 0]}, {"x": 1.255, "y": 5.5, "w": 1.25, "label": "LEFT WIN", "matrix": [5, 1]}, {"x": 2.505, "y": 5.5, "w": 1.25, "label": "LEFT ALT", "matrix": [5, 2]}, {"x": 3.75, "y": 5.5, "w": 6.25, "label": "SPACEBAR", "matrix": [5, 3]}, {"x": 10, "y": 5.5, "w": 1.25, "label": "RIGHT ALT", "matrix": [5, 4]}, {"x": 11.25, "y": 5.5, "w": 1.25, "label": "FN", "matrix": [5, 5]}, {"x": 12.5, "y": 5.5, "w": 1.25, "label": "MENU", "matrix": [5, 6]}, {"x": 13.75, "y": 5.5, "w": 1.25, "label": "RIGHT CTRL", "matrix": [5, 7]}, {"x": 15.5, "y": 5.5, "w": 1, "label": "LEFT ARROW", "matrix": [10, 4]}, {"x": 16.5, "y": 5.5, "w": 1, "label": "DOWN ARROW", "matrix": [10, 5]}, {"x": 17.5, "y": 5.5, "w": 1, "label": "RIGHT ARROW", "matrix": [10, 6]}], "filename": "keyboards/massdrop/ctrl/ctrl.h"}}, "parse_errors": [], "parse_warnings": [], "maintainer": "Massdrop", "url": "https://www.massdrop.com/buy/massdrop-ctrl-mechanical-keyboard", "width": 18.5, "height": 6.5, "diode_direction": null, "matrix_size": {"rows": 11, "cols": 8}, "matrix_pins": {"rows": ["4", " 5", " 6", " 7", " 8", " 9", " 10", " 11", " 10", " 11", " 12"], "cols": ["0", " 1", " 2", " 3", " 4", " 5", " 6", " 7"]}, "usb": {"vid": "0x04D8", "pid": "0xEED2", "device_ver": "0x0101", "manufacturer": "\"Massdrop Inc.\"", "product": "\"CTRL Keyboard\""}, "processor_type": "arm", "bootloader": "unknown", "processor": "cortex-m4", "protocol": "ChibiOS", "platform": "ARM_ATSAM"}}}