{"last_updated": "2021-03-04 01:04:26 GMT", "keyboards": {"wilba_tech/rama_works_m6_b": {"keyboard_name": "RAMA WORKS M6-B", "keyboard_folder": "wilba_tech/rama_works_m6_b", "keymaps": {}, "layouts": {"LAYOUT": {"key_count": 6, "layout": [{"x": 0, "y": 0, "w": 1, "label": "K00", "matrix": [0, 0]}, {"x": 1, "y": 0, "w": 1, "label": "K01", "matrix": [0, 1]}, {"x": 2, "y": 0, "w": 1, "label": "K02", "matrix": [0, 2]}, {"x": 0, "y": 1, "w": 1, "label": "K03", "matrix": [0, 3]}, {"x": 1, "y": 1, "w": 1, "label": "K04", "matrix": [0, 4]}, {"x": 2, "y": 1, "w": 1, "label": "K05", "matrix": [0, 5]}], "filename": "keyboards/wilba_tech/rama_works_m6_b/rama_works_m6_b.h", "c_macro": true}}, "parse_errors": [], "parse_warnings": [], "maintainer": "Wilba", "url": "http://rama.works", "width": 3, "height": 2, "debounce": 5, "usb": {"device_ver": "0x0001", "pid": "0x006B", "vid": "0x5241"}, "diode_direction": "COL2ROW", "manufacturer": "RAMA WORKS", "matrix_size": {"cols": 6, "rows": 1}, "matrix_pins": {"cols": ["D4", "B5", "F4", "D7", "C6", "F6"], "rows": ["E6"]}, "processor": "atmega32u4", "processor_type": "avr", "platform": "unknown", "protocol": "LUFA", "bootloader": "atmel-dfu", "config_h_features": {"mousekey": false, "extrakey": true, "console": false, "command": false, "nkro": true, "backlight": false, "midi": false, "audio": false, "unicode": false, "bluetooth": false, "rgblight": false, "sleep_led": false, "bootmagic_lite": true}, "features": {"mousekey": false, "extrakey": true, "console": false, "command": false, "nkro": true, "backlight": false, "midi": false, "audio": false, "unicode": false, "bluetooth": false, "rgblight": false, "sleep_led": false, "bootmagic_lite": true}}}}